lab_utils/__init__.py
lab_utils/__project__.py
lab_utils/custom_logging.py
lab_utils/database.py
lab_utils/socket_comm.py
lab_utils/conf/database.ini
lab_utils/conf/logging.ini
lab_utils/conf/server.ini
lab_utils-0.5.1.dist-info/LICENSE.md
lab_utils-0.5.1.dist-info/METADATA
lab_utils-0.5.1.dist-info/WHEEL
lab_utils-0.5.1.dist-info/top_level.txt
lab_utils-0.5.1.dist-info/RECORD
