Metadata-Version: 2.1
Name: lab-utils
Version: 0.5.1
Summary: A collection of useful Python modules for laboratory use
Home-page: https://gitlab.ethz.ch/exotic-matter/cw-beam/lab-utils
Author: Carlos Vigo
Author-email: <carlosv@phys.ethz.ch>
License: GPLv3
Keywords: postgres,sql
Platform: UNKNOWN
Classifier: Programming Language :: Python :: 3.6
Classifier: License :: OSI Approved :: GNU General Public License v3 (GPLv3)
Classifier: Operating System :: POSIX :: Linux
Requires-Python: >=3.6
Requires-Dist: psycopg2 (>=2.7)
Requires-Dist: python-json-logger
Requires-Dist: slacker-log-handler
Requires-Dist: zc.lockfile
Provides-Extra: dev
Requires-Dist: flake8 ; extra == 'dev'
Requires-Dist: pytest ; extra == 'dev'
Provides-Extra: docs
Requires-Dist: recommonmark ; extra == 'docs'
Requires-Dist: sphinx ; extra == 'docs'
Requires-Dist: sphinx-paramlinks ; extra == 'docs'
Requires-Dist: sphinx-rtd-theme ; extra == 'docs'
Requires-Dist: wheel ; extra == 'docs'
